mcp_lp_server/__init__.py
mcp_lp_server/__main__.py
mcp_lp_server/gs_web_server.py
mcp_lp_server/main.py
mcp_lp_server/main_debug.py
mcp_lp_server/codegens/gs_options_pb2.py
mcp_lp_server/codegens/gs_options_pb2.pyi
mcp_lp_server/codegens/gravi/cms/cms_content_pb2.py
mcp_lp_server/codegens/gravi/cms/cms_content_pb2.pyi
mcp_lp_server/codegens/gravi/common/gravi_common_pb2.py
mcp_lp_server/codegens/gravi/common/gravi_common_pb2.pyi
mcp_lp_server/codegens/gravi/gsfile/sketch_gsfile_pb2.py
mcp_lp_server/codegens/gravi/gsfile/sketch_gsfile_pb2.pyi
mcp_lp_server/codegens/gravi/gsfile/asset/persistence/asset_pb2.py
mcp_lp_server/codegens/gravi/gsfile/asset/persistence/asset_pb2.pyi
mcp_lp_server/codegens/gravi/gsfile/layergroup/persistence/layer_group_pb2.py
mcp_lp_server/codegens/gravi/gsfile/layergroup/persistence/layer_group_pb2.pyi
mcp_lp_server/codegens/gravi/gsfile/legacy/legacy_gsfile_pb2.py
mcp_lp_server/codegens/gravi/gsfile/legacy/legacy_gsfile_pb2.pyi
mcp_lp_server/codegens/gravi/gsfile/metadata/persistence/metadata_pb2.py
mcp_lp_server/codegens/gravi/gsfile/metadata/persistence/metadata_pb2.pyi
mcp_lp_server/codegens/gravi/gsfile/strokelayer/persistence/layer_pb2.py
mcp_lp_server/codegens/gravi/gsfile/strokelayer/persistence/layer_pb2.pyi
mcp_lp_server/codegens/gravi/library/material_library_pb2.py
mcp_lp_server/codegens/gravi/library/material_library_pb2.pyi
mcp_lp_server/codegens/gravi/localization/localization_pb2.py
mcp_lp_server/codegens/gravi/localization/localization_pb2.pyi
mcp_lp_server/codegens/gravi/models/bot_export_pb2.py
mcp_lp_server/codegens/gravi/models/bot_export_pb2.pyi
mcp_lp_server/codegens/gravi/models/gravi_model_pb2.py
mcp_lp_server/codegens/gravi/models/gravi_model_pb2.pyi
mcp_lp_server/codegens/gravi/models/notifications_pb2.py
mcp_lp_server/codegens/gravi/models/notifications_pb2.pyi
mcp_lp_server/codegens/gravi/models/preferences_pb2.py
mcp_lp_server/codegens/gravi/models/preferences_pb2.pyi
mcp_lp_server-0.1.2.dist-info/METADATA
mcp_lp_server-0.1.2.dist-info/WHEEL
mcp_lp_server-0.1.2.dist-info/entry_points.txt
mcp_lp_server-0.1.2.dist-info/top_level.txt
mcp_lp_server-0.1.2.dist-info/RECORD
