Metadata-Version: 2.4
Name: mcp-lp-server
Version: 0.1.2
Summary: Gravity Sketch Cloud Integration through MCP
Requires-Python: >=3.12
Requires-Dist: httpx>=0.28.1
Requires-Dist: mcp[cli]>=1.5.0
Requires-Dist: protobuf>=6.30.1
Requires-Dist: requests>=2.32.3
